Metadata-Version: 2.1
Name: grouping-list-tuple
Version: 1.0
Summary: Package for grouping array objects in list by some key
Home-page: UNKNOWN
Author: Alex Grishin
Author-email: alexgodlife80@gmail.com
License: MIT
Platform: UNKNOWN
Requires-Python: >=3.9
License-File: LICENCE.txt
